{"id":"chek-list-otkrytie","type":["document"],"name":"Чек-лист открытия счёта","aliases":[],"summary":"Чек-лист открытия лицевого счёта сводит процесс к 14 проверяемым пунктам в четырёх блоках: готовность организации (Сводный реестр, ЕГРЮЛ), доступ (КЭП, МЧД, ГИИС, Континент TLS), комплект документов (заявление, карточка, контракт с ИГК) и подача с контролем сроков. Прохождение всех пунктов до подачи — то, что на практике даёт открытие за 2 рабочих дня.","citation":"Предполётная проверка: исключает типовые причины возвратов и затягивания до подачи комплекта.","pages":[{"layer":"document","url":"/obraztsy/chek-list-otkrytiya-scheta/","title":"Чек-лист открытия счёта"}],"relations":{"RELATED_DOC":["komplekt-otkrytie","zayavlenie-ls","chek-list-dokumenty"],"SEE_ERROR":["err-zatyanulos-otkrytie","err-kartochka"],"MONETIZED_BY":["service-open"],"EXPLAINED_BY_ARTICLE":["/blog/how_to_open/","/blog/sroki-rassmotreniya-dokumentov-v-ufk-tablitsa"]},"updated":"2026-07-09","schema_id":"https://kazna-gov.ru/#e-chek-list-otkrytie","scores":{"authority":44,"coverage":67,"connectivity":100,"citation":80,"aiReadiness":100,"density":100}}